pystasis/__init__.py
pystasis/__main__.py
pystasis/cli.py
pystasis-0.0.3.dist-info/METADATA
pystasis-0.0.3.dist-info/WHEEL
pystasis-0.0.3.dist-info/entry_points.txt
pystasis-0.0.3.dist-info/RECORD
